{
  "annotations": {
    "list": [
      {
        "builtIn": 1,
        "datasource": { "type": "grafana", "uid": "-- Grafana --" },
        "enable": true,
        "hide": true,
        "iconColor": "rgba(0, 211, 255, 1)",
        "name": "Annotations & Alerts",
        "type": "dashboard"
      }
    ]
  },
  "description": "Hive Edge Network — 实时节点状态与性能监控",
  "editable": true,
  "fiscalYearStartMonth": 0,
  "graphTooltip": 1,
  "id": null,
  "links": [],
  "panels": [
    {
      "datasource": { "type": "prometheus", "uid": "${datasource}" },
      "fieldConfig": {
        "defaults": {
          "color": { "mode": "thresholds" },
          "mappings": [],
          "noValue": "0",
          "thresholds": {
            "mode": "absolute",
            "steps": [
              { "color": "green", "value": null }
            ]
          },
          "unit": "short"
        },
        "overrides": []
      },
      "gridPos": { "h": 4, "w": 5, "x": 0, "y": 0 },
      "id": 1,
      "options": {
        "colorMode": "value",
        "graphMode": "none",
        "justifyMode": "center",
        "orientation": "auto",
        "reduceOptions": { "calcs": ["lastNotNull"], "fields": "", "values": false },
        "textMode": "auto",
        "wideLayout": true
      },
      "targets": [
        {
          "datasource": { "type": "prometheus", "uid": "${datasource}" },
          "expr": "count(up{job=\"hives\"} == 1) OR vector(0)",
          "instant": true,
          "legendFormat": "",
          "refId": "A"
        }
      ],
      "title": "Online Nodes",
      "type": "stat"
    },
    {
      "datasource": { "type": "prometheus", "uid": "${datasource}" },
      "fieldConfig": {
        "defaults": {
          "color": { "mode": "thresholds" },
          "mappings": [],
          "noValue": "0",
          "thresholds": {
            "mode": "absolute",
            "steps": [
              { "color": "green", "value": null },
              { "color": "red", "value": 1 }
            ]
          },
          "unit": "short"
        },
        "overrides": []
      },
      "gridPos": { "h": 4, "w": 5, "x": 5, "y": 0 },
      "id": 2,
      "options": {
        "colorMode": "background",
        "graphMode": "none",
        "justifyMode": "center",
        "orientation": "auto",
        "reduceOptions": { "calcs": ["lastNotNull"], "fields": "", "values": false },
        "textMode": "auto",
        "wideLayout": true
      },
      "targets": [
        {
          "datasource": { "type": "prometheus", "uid": "${datasource}" },
          "expr": "count(up{job=\"hives\"} == 0) OR vector(0)",
          "instant": true,
          "legendFormat": "",
          "refId": "A"
        }
      ],
      "title": "Offline Nodes",
      "type": "stat"
    },
    {
      "datasource": { "type": "prometheus", "uid": "${datasource}" },
      "fieldConfig": {
        "defaults": {
          "color": { "fixedColor": "blue", "mode": "fixed" },
          "mappings": [],
          "noValue": "0",
          "thresholds": {
            "mode": "absolute",
            "steps": [{ "color": "blue", "value": null }]
          },
          "unit": "short"
        },
        "overrides": []
      },
      "gridPos": { "h": 4, "w": 4, "x": 10, "y": 0 },
      "id": 3,
      "options": {
        "colorMode": "value",
        "graphMode": "none",
        "justifyMode": "center",
        "orientation": "auto",
        "reduceOptions": { "calcs": ["lastNotNull"], "fields": "", "values": false },
        "textMode": "auto",
        "wideLayout": true
      },
      "targets": [
        {
          "datasource": { "type": "prometheus", "uid": "${datasource}" },
          "expr": "count(up{job=\"hives\"}) OR vector(0)",
          "instant": true,
          "legendFormat": "",
          "refId": "A"
        }
      ],
      "title": "Total Nodes",
      "type": "stat"
    },
    {
      "datasource": { "type": "prometheus", "uid": "${datasource}" },
      "fieldConfig": {
        "defaults": {
          "color": { "mode": "thresholds" },
          "mappings": [
            {
              "options": {
                "0": { "color": "green", "index": 0, "text": "All Systems Operational" }
              },
              "type": "value"
            },
            {
              "options": {
                "from": 1,
                "result": { "color": "red", "index": 1, "text": "Degraded" },
                "to": 10000
              },
              "type": "range"
            }
          ],
          "thresholds": {
            "mode": "absolute",
            "steps": [
              { "color": "green", "value": null },
              { "color": "red", "value": 1 }
            ]
          },
          "unit": "short"
        },
        "overrides": []
      },
      "gridPos": { "h": 4, "w": 10, "x": 14, "y": 0 },
      "id": 4,
      "options": {
        "colorMode": "background",
        "graphMode": "none",
        "justifyMode": "center",
        "orientation": "auto",
        "reduceOptions": { "calcs": ["lastNotNull"], "fields": "", "values": false },
        "text": { "titleSize": 14, "valueSize": 24 },
        "textMode": "value",
        "wideLayout": true
      },
      "targets": [
        {
          "datasource": { "type": "prometheus", "uid": "${datasource}" },
          "expr": "count(up{job=\"hives\"} == 0) OR vector(0)",
          "instant": true,
          "legendFormat": "",
          "refId": "A"
        }
      ],
      "title": "Network Status",
      "type": "stat"
    },
    {
      "datasource": { "type": "prometheus", "uid": "${datasource}" },
      "fieldConfig": {
        "defaults": {
          "color": { "mode": "thresholds" },
          "custom": {
            "fillOpacity": 90,
            "hideFrom": { "legend": false, "tooltip": false, "viz": false },
            "lineWidth": 0
          },
          "mappings": [
            {
              "options": {
                "0": { "color": "red", "index": 0, "text": "Offline" },
                "1": { "color": "green", "index": 1, "text": "Online" }
              },
              "type": "value"
            },
            {
              "options": {
                "match": "null",
                "result": { "color": "red", "index": 2, "text": "Offline" }
              },
              "type": "special"
            }
          ],
          "thresholds": {
            "mode": "absolute",
            "steps": [
              { "color": "red", "value": null },
              { "color": "green", "value": 1 }
            ]
          }
        },
        "overrides": []
      },
      "gridPos": { "h": 9, "w": 24, "x": 0, "y": 4 },
      "id": 5,
      "options": {
        "alignValue": "center",
        "legend": { "displayMode": "list", "placement": "bottom", "showLegend": false },
        "mergeValues": true,
        "rowHeight": 0.85,
        "showValue": "auto",
        "tooltip": { "mode": "single", "sort": "none" }
      },
      "targets": [
        {
          "datasource": { "type": "prometheus", "uid": "${datasource}" },
          "expr": "up{job=\"hives\"}",
          "instant": false,
          "legendFormat": "{{instance}}  {{location}}",
          "refId": "A"
        }
      ],
      "title": "Node Online History",
      "type": "state-timeline"
    },
    {
      "datasource": { "type": "prometheus", "uid": "${datasource}" },
      "fieldConfig": {
        "defaults": {
          "color": { "mode": "palette-classic" },
          "custom": {
            "axisBorderShow": false,
            "axisCenteredZero": false,
            "axisColorMode": "text",
            "axisPlacement": "auto",
            "drawStyle": "line",
            "fillOpacity": 10,
            "gradientMode": "none",
            "hideFrom": { "legend": false, "tooltip": false, "viz": false },
            "insertNulls": false,
            "lineInterpolation": "smooth",
            "lineWidth": 2,
            "pointSize": 5,
            "scaleDistribution": { "type": "linear" },
            "showPoints": "never",
            "spanNulls": true,
            "stacking": { "group": "A", "mode": "none" },
            "thresholdsStyle": { "mode": "line+area" }
          },
          "mappings": [],
          "max": 100,
          "min": 0,
          "thresholds": {
            "mode": "absolute",
            "steps": [
              { "color": "transparent", "value": null },
              { "color": "yellow", "value": 70 },
              { "color": "red", "value": 90 }
            ]
          },
          "unit": "percent"
        },
        "overrides": []
      },
      "gridPos": { "h": 8, "w": 12, "x": 0, "y": 13 },
      "id": 6,
      "options": {
        "legend": {
          "calcs": ["mean", "max"],
          "displayMode": "table",
          "placement": "bottom",
          "showLegend": true
        },
        "tooltip": { "mode": "multi", "sort": "desc" }
      },
      "targets": [
        {
          "datasource": { "type": "prometheus", "uid": "${datasource}" },
          "expr": "100 - (avg by(instance) (rate(node_cpu_seconds_total{mode=\"idle\", job=\"hives\"}[5m])) * 100)",
          "legendFormat": "{{instance}}",
          "refId": "A"
        }
      ],
      "title": "CPU Usage",
      "type": "timeseries"
    },
    {
      "datasource": { "type": "prometheus", "uid": "${datasource}" },
      "fieldConfig": {
        "defaults": {
          "color": { "mode": "palette-classic" },
          "custom": {
            "axisBorderShow": false,
            "axisCenteredZero": false,
            "axisColorMode": "text",
            "axisPlacement": "auto",
            "drawStyle": "line",
            "fillOpacity": 10,
            "gradientMode": "none",
            "hideFrom": { "legend": false, "tooltip": false, "viz": false },
            "insertNulls": false,
            "lineInterpolation": "smooth",
            "lineWidth": 2,
            "pointSize": 5,
            "scaleDistribution": { "type": "linear" },
            "showPoints": "never",
            "spanNulls": true,
            "stacking": { "group": "A", "mode": "none" },
            "thresholdsStyle": { "mode": "line+area" }
          },
          "mappings": [],
          "max": 100,
          "min": 0,
          "thresholds": {
            "mode": "absolute",
            "steps": [
              { "color": "red", "value": null },
              { "color": "yellow", "value": 10 },
              { "color": "green", "value": 20 }
            ]
          },
          "unit": "percent"
        },
        "overrides": []
      },
      "gridPos": { "h": 8, "w": 12, "x": 12, "y": 13 },
      "id": 7,
      "options": {
        "legend": {
          "calcs": ["mean", "min"],
          "displayMode": "table",
          "placement": "bottom",
          "showLegend": true
        },
        "tooltip": { "mode": "multi", "sort": "asc" }
      },
      "targets": [
        {
          "datasource": { "type": "prometheus", "uid": "${datasource}" },
          "expr": "node_memory_MemAvailable_bytes{job=\"hives\"} / node_memory_MemTotal_bytes{job=\"hives\"} * 100",
          "legendFormat": "{{instance}}",
          "refId": "A"
        }
      ],
      "title": "Memory Available %",
      "type": "timeseries"
    },
    {
      "datasource": { "type": "prometheus", "uid": "${datasource}" },
      "fieldConfig": {
        "defaults": {
          "color": { "mode": "thresholds" },
          "mappings": [],
          "min": 0,
          "thresholds": {
            "mode": "absolute",
            "steps": [
              { "color": "red", "value": null },
              { "color": "yellow", "value": 524288000 },
              { "color": "green", "value": 1073741824 }
            ]
          },
          "unit": "bytes"
        },
        "overrides": []
      },
      "gridPos": { "h": 8, "w": 12, "x": 0, "y": 21 },
      "id": 8,
      "options": {
        "displayMode": "gradient",
        "fillOpacity": 80,
        "legend": { "displayMode": "list", "placement": "bottom", "showLegend": true },
        "minVizHeight": 16,
        "minVizWidth": 8,
        "namePlacement": "auto",
        "orientation": "horizontal",
        "reduceOptions": { "calcs": ["lastNotNull"], "fields": "", "values": false },
        "showUnfilled": true,
        "sizing": "auto",
        "tooltip": { "mode": "single", "sort": "none" },
        "valueMode": "color"
      },
      "targets": [
        {
          "datasource": { "type": "prometheus", "uid": "${datasource}" },
          "expr": "node_filesystem_avail_bytes{job=\"hives\", mountpoint=\"/\", fstype!=\"tmpfs\"}",
          "instant": true,
          "legendFormat": "{{instance}}",
          "refId": "A"
        }
      ],
      "title": "Disk Available (Root)",
      "type": "bargauge"
    },
    {
      "datasource": { "type": "prometheus", "uid": "${datasource}" },
      "fieldConfig": {
        "defaults": {
          "color": { "mode": "palette-classic" },
          "custom": {
            "axisBorderShow": false,
            "axisCenteredZero": true,
            "axisColorMode": "text",
            "axisPlacement": "auto",
            "drawStyle": "line",
            "fillOpacity": 10,
            "gradientMode": "none",
            "hideFrom": { "legend": false, "tooltip": false, "viz": false },
            "insertNulls": false,
            "lineInterpolation": "smooth",
            "lineWidth": 1,
            "pointSize": 5,
            "scaleDistribution": { "type": "linear" },
            "showPoints": "never",
            "spanNulls": true,
            "stacking": { "group": "A", "mode": "none" },
            "thresholdsStyle": { "mode": "off" }
          },
          "mappings": [],
          "thresholds": {
            "mode": "absolute",
            "steps": [{ "color": "green", "value": null }]
          },
          "unit": "Bps"
        },
        "overrides": [
          {
            "matcher": { "id": "byNamePattern", "options": "TX.*" },
            "properties": [
              { "id": "custom.transform", "value": "negative-Y" }
            ]
          }
        ]
      },
      "gridPos": { "h": 8, "w": 12, "x": 12, "y": 21 },
      "id": 9,
      "options": {
        "legend": {
          "calcs": ["mean"],
          "displayMode": "table",
          "placement": "bottom",
          "showLegend": true
        },
        "tooltip": { "mode": "multi", "sort": "none" }
      },
      "targets": [
        {
          "datasource": { "type": "prometheus", "uid": "${datasource}" },
          "expr": "sum by(instance) (rate(node_network_receive_bytes_total{job=\"hives\", device!=\"lo\"}[5m]))",
          "legendFormat": "RX  {{instance}}",
          "refId": "A"
        },
        {
          "datasource": { "type": "prometheus", "uid": "${datasource}" },
          "expr": "sum by(instance) (rate(node_network_transmit_bytes_total{job=\"hives\", device!=\"lo\"}[5m]))",
          "legendFormat": "TX  {{instance}}",
          "refId": "B"
        }
      ],
      "title": "Network Traffic",
      "type": "timeseries"
    },
    {
      "datasource": { "type": "prometheus", "uid": "${datasource}" },
      "fieldConfig": {
        "defaults": {
          "color": { "mode": "thresholds" },
          "custom": {
            "align": "auto",
            "cellOptions": { "type": "auto" },
            "filterable": true,
            "inspect": false
          },
          "mappings": [],
          "thresholds": {
            "mode": "absolute",
            "steps": [{ "color": "green", "value": null }]
          }
        },
        "overrides": [
          {
            "matcher": { "id": "byName", "options": "Status" },
            "properties": [
              {
                "id": "mappings",
                "value": [
                  {
                    "options": {
                      "0": { "color": "red", "index": 0, "text": "Offline" },
                      "1": { "color": "green", "index": 1, "text": "Online" }
                    },
                    "type": "value"
                  }
                ]
              },
              { "id": "custom.cellOptions", "value": { "type": "color-background" } },
              { "id": "custom.width", "value": 110 }
            ]
          },
          {
            "matcher": { "id": "byName", "options": "Node" },
            "properties": [
              { "id": "custom.width", "value": 180 }
            ]
          },
          {
            "matcher": { "id": "byName", "options": "Location" },
            "properties": [
              { "id": "custom.width", "value": 130 }
            ]
          },
          {
            "matcher": { "id": "byName", "options": "ID" },
            "properties": [
              { "id": "custom.width", "value": 100 }
            ]
          }
        ]
      },
      "gridPos": { "h": 10, "w": 24, "x": 0, "y": 29 },
      "id": 10,
      "options": {
        "cellHeight": "sm",
        "footer": { "countRows": false, "fields": "", "reducer": ["sum"], "show": false },
        "showHeader": true,
        "sortBy": [{ "desc": false, "displayName": "Node" }]
      },
      "targets": [
        {
          "datasource": { "type": "prometheus", "uid": "${datasource}" },
          "expr": "up{job=\"hives\"}",
          "instant": true,
          "legendFormat": "{{instance}}",
          "refId": "A"
        }
      ],
      "title": "Node Details",
      "transformations": [
        {
          "id": "organize",
          "options": {
            "excludeByName": {
              "Time": true,
              "__name__": true,
              "job": true
            },
            "indexByName": {
              "instance": 0,
              "location": 1,
              "mac6": 2,
              "Value": 3,
              "cf_url": 4
            },
            "renameByName": {
              "Value": "Status",
              "cf_url": "CF URL",
              "instance": "Node",
              "location": "Location",
              "mac6": "ID"
            }
          }
        }
      ],
      "type": "table"
    }
  ],
  "refresh": "1m",
  "schemaVersion": 39,
  "tags": ["hive", "status", "nodes"],
  "templating": {
    "list": [
      {
        "current": {},
        "hide": 2,
        "includeAll": false,
        "multi": false,
        "name": "datasource",
        "options": [],
        "query": "prometheus",
        "refresh": 1,
        "type": "datasource"
      }
    ]
  },
  "time": { "from": "now-6h", "to": "now" },
  "timepicker": {},
  "timezone": "browser",
  "title": "Hive Network Status",
  "uid": "hive-network-status",
  "version": 1
}
